excelbdd/__init__.py
excelbdd/excelbdd.py
excelbdd-1.4.9.dist-info/LICENSE.txt
excelbdd-1.4.9.dist-info/METADATA
excelbdd-1.4.9.dist-info/WHEEL
excelbdd-1.4.9.dist-info/top_level.txt
excelbdd-1.4.9.dist-info/RECORD
