Metadata-Version: 2.1
Name: excelbdd
Version: 1.4.9
Summary: conduct BDD by excel feature files
Author-email: Zhang Keqiang Mike <zhangkq2000@hotmail.com>
Keywords: BDD,Excel,SBE
Classifier: Programming Language :: Python :: 3
Classifier: License :: OSI Approved :: Apache Software License
Classifier: Operating System :: OS Independent
Requires-Python: >=3.9
License-File: LICENSE.txt
Requires-Dist: openpyxl
